static_router/__init__.py
static_router/loaders/__init__.py
static_router/loaders/py.typed
static_router/loaders/static.py
static_router/main.py
static_router/models/__init__.py
static_router/models/content_loader.py
static_router/models/page.py
static_router/models/py.typed
static_router/py.typed
static_router-0.1.0.dist-info/METADATA
static_router-0.1.0.dist-info/WHEEL
static_router-0.1.0.dist-info/RECORD
